stio/__init__.py
stio/matrix_loader.py
stio/chip/__init__.py
stio/chip/encrypted.bin
stio/chip/key.bin
stio/ipr/__init__.py
stio/ipr/ipr_factory.py
stio/ipr/ipr_v0d0d1.py
stio/ipr/ipr_v0d1d0.py
stio/ipr/meta/__init__.py
stio/ipr/meta/hardware.py
stio/ipr/meta/qc.py
stio/ipr/meta/register.py
stio/ipr/meta/research.py
stio/ipr/meta/seg.py
stio/ipr/meta/state.py
stio/ipr/meta/stitch.py
stio/microscopy/__init__.py
stio/microscopy/cg.py
stio/microscopy/dxc.py
stio/microscopy/leica.py
stio/microscopy/motic.py
stio/microscopy/slide_factory.py
stio/microscopy/zeiss.py
stio/rpi/__init__.py
stio/rpi/rpi_v0d0d0.py
stio/rpi/rpi_v0d0d1.py
stio/rpi/rpi_v0d0d2.py
stio/utils/__init__.py
stio/utils/clog.py
stio/utils/file_manager.py
stio/utils/image.py
stio-0.1.0.data/data/encrypted.bin
stio-0.1.0.data/data/key.bin
stio-0.1.0.dist-info/METADATA
stio-0.1.0.dist-info/WHEEL
stio-0.1.0.dist-info/top_level.txt
stio-0.1.0.dist-info/RECORD
