Metadata-Version: 2.1
Name: stio
Version: 0.1.0
Summary: IO for Stereo Cell
Home-page: https://gitlab.genomics.cn/biointelligence/implab/stero-rnd/cellbin/tools/stio/-/tree/dev
Author: jiangqichen
Author-email: jiangqichen@genomics.cn
License: UNKNOWN
Platform: UNKNOWN
Classifier: Development Status :: 3 - Alpha
Classifier: Intended Audience :: Developers
Classifier: License :: OSI Approved :: MIT License
Requires-Python: >=3
Requires-Dist: h5py (==3.8.0)
Requires-Dist: numpy (==1.24.2)
Requires-Dist: pandas (==1.5.3)
Requires-Dist: tifffile (==2023.2.3)
Requires-Dist: tqdm (==4.64.1)
Requires-Dist: colorama (==0.4.6)
Requires-Dist: python-dateutil
Requires-Dist: pytz (==2022.7.1)
Requires-Dist: six (==1.16.0)
Requires-Dist: pycryptodome (==3.17)
Requires-Dist: imagecodecs (==2023.3.16)
